lektor_imgutils.py
lektor_imgutils-0.2.dist-info/LICENSE.txt
lektor_imgutils-0.2.dist-info/METADATA
lektor_imgutils-0.2.dist-info/WHEEL
lektor_imgutils-0.2.dist-info/entry_points.txt
lektor_imgutils-0.2.dist-info/top_level.txt
lektor_imgutils-0.2.dist-info/RECORD
