Metadata-Version: 2.1
Name: lektor-imgutils
Version: 0.2
Summary: Image handling utilities for Lektor.
Author-email: "H. Turgut Uyar" <uyar@tekir.org>
License: Copyright 2023-2024 H. Turgut Uyar <uyar@tekir.org>
Project-URL: repository, https://github.com/uyar/lektor-imgutils
Keywords: lektor,plugin,image,responsive,srcset,picture
Classifier: Development Status :: 4 - Beta
Classifier: Environment :: Plugins
Classifier: Framework :: Lektor
Classifier: Intended Audience :: Developers
Classifier: License :: OSI Approved :: BSD License
Classifier: Programming Language :: Python
Classifier: Programming Language :: Python :: 3.8
Classifier: Programming Language :: Python :: 3.9
Classifier: Programming Language :: Python :: 3.10
Classifier: Programming Language :: Python :: 3.11
Classifier: Programming Language :: Python :: 3.12
Classifier: Topic :: Internet :: WWW/HTTP :: Site Management
Requires-Python: ~=3.8
License-File: LICENSE.txt
Requires-Dist: lektor
Requires-Dist: lxml
Requires-Dist: cssselect
Requires-Dist: pillow
Requires-Dist: typedload
Provides-Extra: dev
Requires-Dist: lektor-imgutils[style,tests,types] ; extra == 'dev'
Requires-Dist: build ; extra == 'dev'
Requires-Dist: twine ; extra == 'dev'
Requires-Dist: tox ; extra == 'dev'
Provides-Extra: style
Requires-Dist: ruff ; extra == 'style'
Provides-Extra: tests
Requires-Dist: pytest ; extra == 'tests'
Requires-Dist: pytest-cov ; extra == 'tests'
Provides-Extra: types
Requires-Dist: mypy ; extra == 'types'
Requires-Dist: lxml-stubs ; extra == 'types'
